LICENSE.txt
MANIFEST.in
README.md
setup.cfg
setup.py
browserstack_sdk/__init__.py
browserstack_sdk/_version.py
browserstack_sdk/browserstack.framework.yml.sample
browserstack_sdk/browserstack.generic.yml.sample
browserstack_sdk/bstack111111ll1l_opy_.py
browserstack_sdk/bstack11111lll11_opy_.py
browserstack_sdk/bstack111ll1ll_opy_.py
browserstack_sdk/bstack11l11111l1_opy_.py
browserstack_sdk/bstack11l11l11l_opy_.py
browserstack_sdk/bstack1lll111lll_opy_.py
browserstack_sdk/bstack1lll11ll1_opy_.py
browserstack_sdk/bstack_behave_runner.py
browserstack_sdk/bstack_robot_listener.py
browserstack_sdk/sdk_pb2.py
browserstack_sdk/sdk_pb2_grpc.py
browserstack_sdk.egg-info/PKG-INFO
browserstack_sdk.egg-info/SOURCES.txt
browserstack_sdk.egg-info/dependency_links.txt
browserstack_sdk.egg-info/entry_points.txt
browserstack_sdk.egg-info/requires.txt
browserstack_sdk.egg-info/top_level.txt
browserstack_sdk/assets/report.html
browserstack_sdk/sdk_cli/__init__.py
browserstack_sdk/sdk_cli/bstack11ll111ll_opy_.py
browserstack_sdk/sdk_cli/bstack1l1ll11111l_opy_.py
browserstack_sdk/sdk_cli/bstack1ll11ll11ll_opy_.py
browserstack_sdk/sdk_cli/bstack1ll11lll1l1_opy_.py
browserstack_sdk/sdk_cli/bstack1ll1l11111l_opy_.py
browserstack_sdk/sdk_cli/bstack1ll1l1l111l_opy_.py
browserstack_sdk/sdk_cli/bstack1ll1l1ll111_opy_.py
browserstack_sdk/sdk_cli/bstack1ll1lllll1l_opy_.py
browserstack_sdk/sdk_cli/bstack1lll111l1ll_opy_.py
browserstack_sdk/sdk_cli/bstack1lll11l1lll_opy_.py
browserstack_sdk/sdk_cli/bstack1lll11ll1ll_opy_.py
browserstack_sdk/sdk_cli/bstack1lll1l111ll_opy_.py
browserstack_sdk/sdk_cli/bstack1lll1l11l11_opy_.py
browserstack_sdk/sdk_cli/bstack1lll1l1l1l1_opy_.py
browserstack_sdk/sdk_cli/bstack1lll1ll1l11_opy_.py
browserstack_sdk/sdk_cli/bstack1llll111l11_opy_.py
browserstack_sdk/sdk_cli/bstack1llll1llll1_opy_.py
browserstack_sdk/sdk_cli/cli.py
browserstack_sdk/sdk_cli/pytest_bdd_framework.py
browserstack_sdk/sdk_cli/test_framework.py
browserstack_sdk/sdk_cli/utils/__init__.py
browserstack_sdk/sdk_cli/utils/bstack11lll1l1l_opy_.py
browserstack_sdk/sdk_cli/utils/bstack1ll1llll11l_opy_.py
bstack_utils/__init__.py
bstack_utils/accessibility.py
bstack_utils/bstack1111111lll_opy_.py
bstack_utils/bstack11111ll1_opy_.py
