Metadata-Version: 1.0
Name: browserstack-sdk
Version: 1.34.0
Summary: Python SDK for browserstack selenium-webdriver tests
Home-page: UNKNOWN
Author: BrowserStack
Author-email: support@browserstack.com
License: BrowserStack Software License Agreement
Keywords: browserstack,selenium,python
Platform: UNKNOWN
